<?xml version="1.0" encoding="UTF-8"?>
<databaseChangeLog
	xmlns:xsi="http://www.w3.org/2001/XMLSchema-instance"
	xmlns:ext="http://www.liquibase.org/xml/ns/dbchangelog-ext"
	xmlns="http://www.liquibase.org/xml/ns/dbchangelog"
	xsi:schemaLocation="http://www.liquibase.org/xml/ns/dbchangelog http://www.liquibase.org/xml/ns/dbchangelog/dbchangelog-3.1.xsd
    http://www.liquibase.org/xml/ns/dbchangelog-ext http://www.liquibase.org/xml/ns/dbchangelog/dbchangelog-ext.xsd">
	<changeSet author="admin" id="1">
		<createTable tableName="app_users">
			<column name="id" type="int" autoIncrement="true">
				<constraints nullable="false" primaryKey="true" />
			</column>
			<column name="name" type="varchar(100)">
				<constraints nullable="false" />
			</column>
			<column name="username" type="varchar(50)">
				<constraints nullable="false" />
			</column>
			<column name="password" type="varchar(100)">
				<constraints nullable="false" />
			</column>
		</createTable>
		
		<createTable tableName="category">
			<column name="id" type="int" autoIncrement="true">
				<constraints nullable="false" primaryKey="true" />
			</column>
			<column name="name" type="varchar(100)">
				<constraints nullable="false" />
			</column>
		</createTable>
		
		<createTable tableName="budget">
			<column name="id" type="int" autoIncrement="true">
				<constraints nullable="false" primaryKey="true" />
			</column>
			<column name="app_user" type="int">
				<constraints nullable="false"
					foreignKeyName="user_budget" references="app_users(id)" />
			</column>
			<column name="start_date" type="timestamp with time zone"/>
			<column name="end_date" type="timestamp with time zone"/>
		</createTable>
		
		<createTable tableName="budget_categories">
			<column name="category_id" type="int">
				<constraints nullable="false"
					foreignKeyName="category_bud_cat" references="category(id)" />
			</column>
			<column name="budget_id" type="int">
				<constraints nullable="false"
					foreignKeyName="budget_bud_cat" references="budget(id)" />
			</column>
			<column name="value" type="currency">
				<constraints nullable="false" />
			</column>
		</createTable>
		
		<createTable tableName="expense">
			<column name="id" type="int" autoIncrement="true">
				<constraints nullable="false" primaryKey="true" />
			</column>
			<column name="category" type="int">
				<constraints nullable="false"
					foreignKeyName="category_expense" references="category(id)" />
			</column>
			<column name="app_user" type="int">
				<constraints nullable="false"
					foreignKeyName="user_expense" references="app_users(id)" />
			</column>
			<column name="name" type="varchar(100)">
				<constraints nullable="false" />
			</column>
			<column name="value" type="currency">
				<constraints nullable="false" />
			</column>
			<column name="expire_at" type="timestamp with time zone"/>
		</createTable>
		
		<createTable tableName="income">
			<column name="id" type="int" autoIncrement="true">
				<constraints nullable="false" primaryKey="true" />
			</column>
			<column name="app_user" type="int">
				<constraints nullable="false"
					foreignKeyName="user_income" references="app_users(id)" />
			</column>
			<column name="name" type="varchar(100)">
				<constraints nullable="false" />
			</column>
			<column name="value" type="currency">
				<constraints nullable="false" />
			</column>
			<column name="date" type="timestamp with timezone"/>
		</createTable>
		
	</changeSet>
</databaseChangeLog>